geosdhydro-0.5.0.dist-info/METADATA
geosdhydro-0.5.0.dist-info/WHEEL
geosdhydro-0.5.0.dist-info/entry_points.txt
geosdhydro-0.5.0.dist-info/licenses/LICENSE
geosdhydro/__init__.py
geosdhydro/__main__.py
geosdhydro/_internal/__init__.py
geosdhydro/_internal/cli.py
geosdhydro/_internal/debug.py
geosdhydro/_internal/swift.py
geosdhydro/py.typed
geosdhydro-0.5.0.dist-info/RECORD
