Metadata-Version: 2.4
Name: geosdhydro
Version: 0.5.0
Summary: GIS tools for semi-distributed hydrologic modelling
Author-Email: J-M <jean-michel.perraud@csiro.au>
License-Expression: BSD-3-Clause
License-File: LICENSE
Classifier: Development Status :: 4 - Beta
Classifier: Intended Audience :: Developers
Classifier: Programming Language :: Python
Classifier: Programming Language :: Python :: 3
Classifier: Programming Language :: Python :: 3 :: Only
Classifier: Programming Language :: Python :: 3.9
Classifier: Programming Language :: Python :: 3.10
Classifier: Programming Language :: Python :: 3.11
Classifier: Programming Language :: Python :: 3.12
Classifier: Programming Language :: Python :: 3.13
Classifier: Programming Language :: Python :: 3.14
Classifier: Topic :: Documentation
Classifier: Topic :: Software Development
Classifier: Topic :: Utilities
Classifier: Typing :: Typed
Project-URL: Homepage, https://csiro-hydroinformatics.github.io/geosdhydro
Project-URL: Documentation, https://csiro-hydroinformatics.github.io/geosdhydro
Project-URL: Changelog, https://csiro-hydroinformatics.github.io/geosdhydro/changelog
Project-URL: Repository, https://github.com/csiro-hydroinformatics/geosdhydro
Project-URL: Issues, https://github.com/csiro-hydroinformatics/geosdhydro/issues
Project-URL: Discussions, https://github.com/csiro-hydroinformatics/geosdhydro/discussions
Requires-Python: >=3.9
Requires-Dist: geopandas
